geotex.cpython-38-x86_64-linux-gnu.so
lib64/libgeogram.a
lib64/pkgconfig/geogram1.pc
lib64/cmake/modules/FindGeogram.cmake
geotex-0.1.1.dist-info/WHEEL
geotex-0.1.1.dist-info/METADATA
geotex-0.1.1.dist-info/RECORD
geotex-0.1.1.dist-info/licenses/LICENSE
geotex.libs/libgomp-a34b3233.so.1.0.0
include/geogram1/geogram/numerics/optimizer.h
include/geogram1/geogram/numerics/interval_nt.h
include/geogram1/geogram/numerics/lbfgs_optimizers.h
include/geogram1/geogram/numerics/exact_geometry.h
include/geogram1/geogram/numerics/PCK.h
include/geogram1/geogram/numerics/matrix_util.h
include/geogram1/geogram/numerics/predicates.h
include/geogram1/geogram/numerics/multi_precision.h
include/geogram1/geogram/numerics/expansion_nt.h
include/geogram1/geogram/numerics/predicates/det4d.h
include/geogram1/geogram/numerics/predicates/det3d.h
include/geogram1/geogram/numerics/predicates/dot3d.h
include/geogram1/geogram/numerics/predicates/side3h.h
include/geogram1/geogram/numerics/predicates/aligned3d.h
include/geogram1/geogram/numerics/predicates/side2.h
include/geogram1/geogram/numerics/predicates/side4h.h
include/geogram1/geogram/numerics/predicates/side3.h
include/geogram1/geogram/numerics/predicates/side4.h
include/geogram1/geogram/numerics/predicates/det_compare_4d.h
include/geogram1/geogram/numerics/predicates/side3_2dlifted.h
include/geogram1/geogram/numerics/predicates/dot_compare_3d.h
include/geogram1/geogram/numerics/predicates/orient2d.h
include/geogram1/geogram/numerics/predicates/orient4d.h
include/geogram1/geogram/numerics/predicates/orient3d.h
include/geogram1/geogram/numerics/predicates/side1.h
include/geogram1/geogram/basic/b_stream.h
include/geogram1/geogram/basic/environment.h
include/geogram1/geogram/basic/thread_sync.h
include/geogram1/geogram/basic/geofile.h
include/geogram1/geogram/basic/geometry.h
include/geogram1/geogram/basic/packed_arrays.h
include/geogram1/geogram/basic/rationalg.h
include/geogram1/geogram/basic/counted.h
include/geogram1/geogram/basic/determinant.h
include/geogram1/geogram/basic/common.h
include/geogram1/geogram/basic/argused.h
