Metadata-Version: 2.2
Name: geotex
Version: 0.1.1
Summary: Geogram texturing (atlas) bindings
Author-Email: Mark Boss <hello@markboss.me>
License: BSD-3-Clause
Classifier: Programming Language :: Python :: 3
Classifier: Programming Language :: C++
Classifier: License :: OSI Approved :: BSD License
Classifier: Operating System :: OS Independent
Requires-Python: >=3.8
Requires-Dist: numpy>=1.20.0
Provides-Extra: dev
Requires-Dist: pytest>=7.0.0; extra == "dev"
